armadillin-0.53.dist-info/METADATA
armadillin-0.53.dist-info/RECORD
armadillin-0.53.dist-info/WHEEL
armadillin-0.53.dist-info/entry_points.txt
armadillin-0.53.dist-info/top_level.txt
armadillin/input.py
armadillin/helpers_compiled.pyx
armadillin/training_make_input.py
armadillin/helpers_compiled.c
armadillin/__init__.py
armadillin/_version.py
armadillin/training_input.py
armadillin/train.py
armadillin/modelling.py
armadillin/__main__.py
armadillin/cov2_genome.py
armadillin/training_create_small_model.py
armadillin/helpers_compiled.pypy37-pp73-i686-linux-gnu.so
