Metadata-Version: 2.1
Name: armadillin
Version: 0.53
Summary: Lineage prediction from SARS-CoV-2 sequences
Home-page: https://github.com/theosanderson/armadillin
Author: Theo Sanderson
Author-email: theo@theo.io
License: UNKNOWN
Project-URL: Bug Tracker, https://github.com/theosanderson/armadillin/issues
Platform: UNKNOWN
Classifier: Programming Language :: Python :: 3
Classifier: License :: OSI Approved :: MIT License
Classifier: Operating System :: OS Independent
Requires-Python: >=3.6
Requires-Dist: tensorflow (==2.6.0)
Requires-Dist: keras (==2.6.0)
Requires-Dist: tqdm
Requires-Dist: biopython
Requires-Dist: tensorflow-model-optimization (==0.7.0)
Requires-Dist: pandas
Requires-Dist: numpy
Requires-Dist: cython
Requires-Dist: armadillin-model
Requires-Dist: flowalign
